{
  "$schema": "https://raw.githubusercontent.com/DotNetAnalyzers/StyleCopAnalyzers/master/StyleCop.Analyzers/StyleCop.Analyzers/Settings/stylecop.schema.json",
  "settings": {
    "documentationRules": {
      "copyrightText": "Copyright (c) {ownerName}, {year}. All rights reserved.\nLicensed under the {licenseName} license. See the {licenseFile} file in the project root for full license information.",
      "documentExposedElements": true,
      "documentInterfaces": true,
      "documentInternalElements": false,
      "documentPrivateElements": false,
      "documentPrivateFields": false,
      "fileNamingConvention": "metadata",
      "xmlHeader": false,
      "variables": {
        "licenseFile": "LICENSE",
        "licenseName": "Apache 2.0",
        "ownerName": "Just Eat",
        "year": "2017"
      }
    },
    "layoutRules": {
      "newlineAtEndOfFile": "require"
    },
    "maintainabilityRules": {},
    "namingRules": {
      "allowCommonHungarianPrefixes": true,
      "allowedHungarianPrefixes": []
    },
    "orderingRules": {
      "elementOrder": [
        "kind",
        "accessibility",
        "constant",
        "static",
        "readonly"
      ],
      "systemUsingDirectivesFirst": true,
      "usingDirectivesPlacement": "outsideNamespace"
    },
    "readabilityRules": {},
    "spacingRules": {}
  }
}
